kptop_tool.py
kubePtop/__init__.py
kubePtop/ascii_graph.py
kubePtop/cli_args.py
kubePtop/colors.py
kubePtop/command_run.py
kubePtop/command_yaml_loader.py
kubePtop/dashboard_monitor.py
kubePtop/dashboard_yaml_loader.py
kubePtop/global_attrs.py
kubePtop/helper.py
kubePtop/logging.py
kubePtop/read_env.py
kubePtop/session.py
kptop-0.0.11.dist-info/LICENSE
kptop-0.0.11.dist-info/METADATA
kptop-0.0.11.dist-info/WHEEL
kptop-0.0.11.dist-info/entry_points.txt
kptop-0.0.11.dist-info/top_level.txt
kptop-0.0.11.dist-info/RECORD
